[{"path":"/muneeb-mbytes/verilator/wiki","title":"Home · muneeb-mbytes/verilator Wiki","count":40,"uniques":10},{"path":"/muneeb-mbytes/verilator/wiki/Installing-Verilator-via-WSL","title":"Installing Verilator via WSL · muneeb-mbytes/verilator Wiki · GitHub","count":31,"uniques":12},{"path":"/muneeb-mbytes/verilator/wiki/Installation-steps","title":"Installation steps · muneeb-mbytes/verilator Wiki","count":20,"uniques":9},{"path":"/muneeb-mbytes/verilator","title":"muneeb-mbytes/verilator: Verilator open-source SystemVerilog simulator and li...","count":19,"uniques":12},{"path":"/muneeb-mbytes/verilator/tree/master/docs","title":"verilator/docs at master · muneeb-mbytes/verilator","count":8,"uniques":1},{"path":"/muneeb-mbytes/verilator/wiki/Introduction","title":"Introduction · muneeb-mbytes/verilator Wiki · GitHub","count":5,"uniques":4},{"path":"/muneeb-mbytes/verilator/tree/master/docs/guide","title":"verilator/docs/guide at master · muneeb-mbytes/verilator","count":4,"uniques":1},{"path":"/muneeb-mbytes/verilator/wiki/Verilator-Windows-Installation-Procedure","title":"Verilator Windows Installation Procedure · muneeb-mbytes/verilator Wiki","count":3,"uniques":2},{"path":"/muneeb-mbytes/verilator/graphs/commit-activity","title":"Commit Activity · muneeb-mbytes/verilator · GitHub","count":2,"uniques":1},{"path":"/muneeb-mbytes/verilator/graphs/contributors","title":"Contributors to muneeb-mbytes/verilator · GitHub","count":1,"uniques":1}]